canarython/__init__.py
canarython/canarython.py
Canarython-0.0.1.dist-info/LICENSE
Canarython-0.0.1.dist-info/METADATA
Canarython-0.0.1.dist-info/WHEEL
Canarython-0.0.1.dist-info/entry_points.txt
Canarython-0.0.1.dist-info/top_level.txt
Canarython-0.0.1.dist-info/RECORD
