Metadata-Version: 2.1
Name: Canarython
Version: 0.0.1
Summary: Generate 'Warrant Cannaries' easily
Author: TheToddLuci0
Project-URL: Homepage, https://github.com/TheToddLuci0/canarython
Project-URL: Bug Tracker, https://github.com/TheToddLuci0/canarython/issues
Classifier: Programming Language :: Python :: 3
Classifier: License :: OSI Approved :: MIT License
Classifier: Operating System :: OS Independent
Requires-Python: >=3.7
License-File: LICENSE
Requires-Dist: feedparser
